calcu/__init__.py
calcu/calcapp.py
calcu/controller.py
calcu/model_calc.py
calcu/view.py
calcudeRoger/__init__.py
calcudeRoger/calcapp.py
calcudeRoger/controller.py
calcudeRoger/model_calc.py
calcudeRoger/view.py
calcudeRoger/otrom/__init__.py
calcudeRoger/otrom/calcapp.py
calcudeRoger/otrom/controller.py
calcudeRoger/otrom/model_calc.py
calcudeRoger/otrom/view.py
calcudeRoger-0.0.5.dist-info/LICENSE
calcudeRoger-0.0.5.dist-info/METADATA
calcudeRoger-0.0.5.dist-info/WHEEL
calcudeRoger-0.0.5.dist-info/top_level.txt
calcudeRoger-0.0.5.dist-info/RECORD
