Metadata-Version: 2.1
Name: calcudeRoger
Version: 0.0.5
Summary: Simple test package
Author: Roger
License-File: LICENSE
Requires-Dist: CoolProp
